fml_library/__init__.py
fml_library/KNN/KNN.py
fml_library/KNN/Utility_functions.py
fml_library/KNN/__init__.py
fml_library/KNN/testing.py
fml_library/Kernals/__init__.py
fml_library/Kernals/kernals.py
fml_library/Naive_Bayes/__init__.py
fml_library/Naive_Bayes/naive_bayes.py
fml_library/Naive_Bayes/tester.py
fml_library/SVM/__init__.py
fml_library/SVM/svm.py
fml_library/SVM/tester.py
fml_library-1.0.dist-info/METADATA
fml_library-1.0.dist-info/WHEEL
fml_library-1.0.dist-info/top_level.txt
fml_library-1.0.dist-info/RECORD
