Metadata-Version: 2.1
Name: fml-library
Version: 1.0
Requires-Dist: numpy
Requires-Dist: pandas
Requires-Dist: scikit-learn
